README.md
setup.cfg
setup.py
rest_tracker/__init__.py
rest_tracker/admin.py
rest_tracker/apps.py
rest_tracker/decorators.py
rest_tracker/models.py
rest_tracker/serializers.py
rest_tracker/tasks.py
rest_tracker/tests.py
rest_tracker/urls.py
rest_tracker/views.py
rest_tracker.egg-info/PKG-INFO
rest_tracker.egg-info/SOURCES.txt
rest_tracker.egg-info/dependency_links.txt
rest_tracker.egg-info/requires.txt
rest_tracker.egg-info/top_level.txt
rest_tracker/migrations/__init__.py